[{"id":1084728,"title":"Asterix: The Kingdom of Nubia","release_date":"2026-12-03","poster_path":"/auCAWHqfoaO3aoOdvJRBARxv5Mv.jpg","backdrop_path":"/gFbCOBwB9qEptHJY230sNCsyZfX.jpg","vote_average":0,"vote_count":0,"genre_ids":[16,12,35,10751,14],"overview":"The irreductible Gauls are turned into harmless children after a rare youth elixir accidentally ends up into the magic potion. To find the antidote and save the village from the Romans attack, Asterix and Obelix embark on a crazy journey to the far away Kingdom of Nubia.","original_language":"fr","directors":["Alexandre Heboyan"],"cast":["Christian Clavier","François-Xavier Demaison","Bernard Alane","Issa Doumbia","François de Brauer"],"slug":"asterix-the-kingdom-of-nubia"}]